omnidim_mcp_server/__init__.py
omnidim_mcp_server/main.py
omnidimension/__init__.py
omnidimension/client.py
omnidimension/Agent/__init__.py
omnidimension/BulkCall/__init__.py
omnidimension/Call/__init__.py
omnidimension/Integrations/__init__.py
omnidimension/KnowledgeBase/__init__.py
omnidimension/PhoneNumber/__init__.py
omnidimension/Providers/__init__.py
omnidimension/Simulation/__init__.py
omnidimension-0.2.16.dist-info/LICENSE
omnidimension-0.2.16.dist-info/METADATA
omnidimension-0.2.16.dist-info/WHEEL
omnidimension-0.2.16.dist-info/entry_points.txt
omnidimension-0.2.16.dist-info/top_level.txt
omnidimension-0.2.16.dist-info/RECORD
