Metadata-Version: 2.1
Name: omnidimension
Version: 0.2.16
Summary: SDK and MCP Server for Omni Assistant services
Home-page: https://github.com/kevin-omnidim/omnidim-sdk
Author: https://www.omnidim.io/
Author-email: kevin@omnidim.io
Classifier: Programming Language :: Python :: 3
Classifier: License :: OSI Approved :: MIT License
Classifier: Operating System :: OS Independent
Requires-Python: >=3.6
License-File: LICENSE
Requires-Dist: requests
Provides-Extra: mcp
Requires-Dist: fastapi>=0.95.0; extra == "mcp"
Requires-Dist: uvicorn>=0.21.0; extra == "mcp"
Requires-Dist: fastmcp>=0.1.0; extra == "mcp"
Requires-Dist: pydantic>=1.10.0; extra == "mcp"
